tensor_network/__init__.py
tensor_network/_modidx.py
tensor_network/eigen_decomposition.py
tensor_network/feature_mapping.py
tensor_network/setup_ref_code_import.py
tensor_network/algorithms/__init__.py
tensor_network/algorithms/calc_ground_state_linear_operator.py
tensor_network/algorithms/dyn_feature_selection_OEE.py
tensor_network/algorithms/entanglement_ordered_sampling_protocal.py
tensor_network/algorithms/gmps.py
tensor_network/algorithms/imaginary_time_evolution.py
tensor_network/algorithms/lazy_classifier.py
tensor_network/algorithms/quantum_kernels.py
tensor_network/algorithms/tensor_decomposition.py
tensor_network/algorithms/time_evolving_block_decimation.py
tensor_network/mlx/__init__.py
tensor_network/mlx/eigen_decomposition.py
tensor_network/mlx/networks/__init__.py
tensor_network/mlx/networks/res_mps.py
tensor_network/mlx/utils/__init__.py
tensor_network/mlx/utils/tensors.py
tensor_network/mps/__init__.py
tensor_network/mps/functional.py
tensor_network/mps/modules.py
tensor_network/networks/__init__.py
tensor_network/networks/adqc.py
tensor_network/networks/fc.py
tensor_network/networks/hybrid.py
tensor_network/networks/qrnn.py
tensor_network/networks/res_mps.py
tensor_network/networks/time_evolution.py
tensor_network/quantum_state/__init__.py
tensor_network/quantum_state/functional.py
tensor_network/tensor_gates/__init__.py
tensor_network/tensor_gates/functional.py
tensor_network/tensor_gates/hamiltonians.py
tensor_network/tensor_gates/modules.py
tensor_network/utils/__init__.py
tensor_network/utils/checking.py
tensor_network/utils/data.py
tensor_network/utils/mapping.py
tensor_network/utils/tensors.py
tensor_network_code-0.2.0.dist-info/METADATA
tensor_network_code-0.2.0.dist-info/WHEEL
tensor_network_code-0.2.0.dist-info/licenses/LICENSE
tensor_network_code-0.2.0.dist-info/RECORD
