Metadata-Version: 2.4
Name: tensor-network-code
Version: 0.2.0
Summary: Tensor Network Code
License-File: LICENSE
Requires-Python: >=3.12
Requires-Dist: einops
Requires-Dist: numpy>=2.2.3
Requires-Dist: scikit-learn>=1.6.1
Requires-Dist: scipy>=1.15.2
Provides-Extra: mlx
Requires-Dist: mlx>=0.26.0; extra == 'mlx'
